telliot_feed_examples/__init__.py
telliot_feed_examples/__main__.py
telliot_feed_examples/cli.py
telliot_feed_examples/feeds/__init__.py
telliot_feed_examples/feeds/ampl_usd_vwap_feed.py
telliot_feed_examples/feeds/bct_usd_feed.py
telliot_feed_examples/feeds/btc_usd_feed.py
telliot_feed_examples/feeds/dai_usd_feed.py
telliot_feed_examples/feeds/diva_protocol_feed.py
telliot_feed_examples/feeds/eth_jpy_feed.py
telliot_feed_examples/feeds/eth_usd_feed.py
telliot_feed_examples/feeds/idle_usd_feed.py
telliot_feed_examples/feeds/matic_usd_feed.py
telliot_feed_examples/feeds/mkr_usd_feed.py
telliot_feed_examples/feeds/olympus.py
telliot_feed_examples/feeds/ric_usd_feed.py
telliot_feed_examples/feeds/sushi_usd_feed.py
telliot_feed_examples/feeds/trb_usd_feed.py
telliot_feed_examples/feeds/usdc_usd_feed.py
telliot_feed_examples/feeds/uspce_feed.py
telliot_feed_examples/feeds/vesq.py
telliot_feed_examples/flashbots/__init__.py
telliot_feed_examples/flashbots/flashbots.py
telliot_feed_examples/flashbots/middleware.py
telliot_feed_examples/flashbots/provider.py
telliot_feed_examples/flashbots/types.py
telliot_feed_examples/reporters/__init__.py
telliot_feed_examples/reporters/flashbot.py
telliot_feed_examples/reporters/interval.py
telliot_feed_examples/reporters/tellorflex.py
telliot_feed_examples/sources/__init__.py
telliot_feed_examples/sources/ampl_usd_vwap.py
telliot_feed_examples/sources/diva_protocol.py
telliot_feed_examples/sources/price_aggregator.py
telliot_feed_examples/sources/uspce.py
telliot_feed_examples/sources/price/__init__.py
telliot_feed_examples/sources/price/historical/__init__.py
telliot_feed_examples/sources/price/historical/cryptowatch.py
telliot_feed_examples/sources/price/historical/kraken.py
telliot_feed_examples/sources/price/historical/poloniex.py
telliot_feed_examples/sources/price/spot/__init__.py
telliot_feed_examples/sources/price/spot/binance.py
telliot_feed_examples/sources/price/spot/bitfinex.py
telliot_feed_examples-0.0.14.dist-info/LICENSE
telliot_feed_examples-0.0.14.dist-info/METADATA
telliot_feed_examples-0.0.14.dist-info/WHEEL
telliot_feed_examples-0.0.14.dist-info/entry_points.txt
telliot_feed_examples-0.0.14.dist-info/top_level.txt
telliot_feed_examples-0.0.14.dist-info/RECORD
