Metadata-Version: 2.1
Name: telliot-feed-examples
Version: 0.0.14
Summary: Contains examples and plugins for reporting to the TellorX Oracle.
Home-page: https://github.com/tellor-io/telliot-feed-examples
Author: Tellor Development Community
Author-email: info@tellor.io
License: MIT
Keywords: oracle,ethereum,blockchain
Platform: UNKNOWN
Classifier: Development Status :: 3 - Alpha
Classifier: Intended Audience :: Developers
Classifier: Intended Audience :: Financial and Insurance Industry
Classifier: Intended Audience :: Information Technology
Classifier: Intended Audience :: Science/Research
Classifier: Topic :: Scientific/Engineering :: Mathematics
Classifier: Topic :: System :: Networking
Classifier: Topic :: Office/Business :: Financial
Classifier: License :: OSI Approved :: MIT License
Classifier: Programming Language :: Python :: 3.9
Requires-Python: >=3.9
License-File: LICENSE
Requires-Dist: telliot-core (>=0.1.4)
Requires-Dist: pydantic
Requires-Dist: python-dotenv
